langchain_mcp_m2m/__init__.py
langchain_mcp_m2m/client.py
langchain_mcp_m2m/client_credentials_auth.py
langchain_mcp_m2m/errors.py
langchain_mcp_m2m/httpx_auth.py
langchain_mcp_m2m-0.1.0.dist-info/METADATA
langchain_mcp_m2m-0.1.0.dist-info/WHEEL
langchain_mcp_m2m-0.1.0.dist-info/licenses/LICENSE
langchain_mcp_m2m-0.1.0.dist-info/RECORD
